<?xml version="1.0" encoding="utf-8"?>
<WLDRecords>
    <WLD Num="363">
        <Name>F-15E Center</Name>
        <WpnIdx_0>362</WpnIdx_0>
        <WpnIdx_1>286</WpnIdx_1>
        <WpnIdx_2>287</WpnIdx_2>
        <WpnIdx_3>288</WpnIdx_3>
        <WpnIdx_4>292</WpnIdx_4>
        <WpnIdx_5>293</WpnIdx_5>
        <WpnIdx_6>363</WpnIdx_6>
        <WpnIdx_7>105</WpnIdx_7>
        <WpnCount_0>1</WpnCount_0>
        <WpnCount_1>1</WpnCount_1>
        <WpnCount_2>1</WpnCount_2>
        <WpnCount_3>1</WpnCount_3>
        <WpnCount_4>1</WpnCount_4>
        <WpnCount_5>1</WpnCount_5>
        <WpnCount_6>1</WpnCount_6>
        <WpnCount_7>1</WpnCount_7>
    </WLD>
</WLDRecords>
